drumpy/__init__.py
drumpy/main.py
drumpy/static/keymap.yaml
drumpy/static/samples/bass/1.wav
drumpy/static/samples/bass/2.wav
drumpy/static/samples/bass/3.wav
drumpy/static/samples/bass/4.wav
drumpy/static/samples/closed_hh/1.wav
drumpy/static/samples/closed_hh/2.wav
drumpy/static/samples/crash/1.wav
drumpy/static/samples/crash/2.wav
drumpy/static/samples/crash/3.wav
drumpy/static/samples/open_hh/1.wav
drumpy/static/samples/open_hh/2.wav
drumpy/static/samples/open_hh/3.wav
drumpy/static/samples/snare/1.wav
drumpy/static/samples/snare/2.wav
drumpy/static/samples/snare/3.wav
drumpy/static/samples/toms/1.wav
drumpy/static/samples/toms/2.wav
drumpy/static/samples/toms/3.wav
drumpy/static/samples/toms/4.wav
drumpy/static/samples/toms/5.wav
drumpy/static/samples/toms/6.wav
drumpy/static/samples/toms/7.wav
drumpy/static/samples/toms/8.wav
drumpy/static/samples/toms/9.wav
drumpy-0.1.0.dist-info/LICENSE
drumpy-0.1.0.dist-info/METADATA
drumpy-0.1.0.dist-info/WHEEL
drumpy-0.1.0.dist-info/entry_points.txt
drumpy-0.1.0.dist-info/top_level.txt
drumpy-0.1.0.dist-info/RECORD
