Metadata-Version: 2.1
Name: drumpy
Version: 0.1.0
Summary: Play drums on your keyboard
Home-page: https://github.com/olbed/drumpy
Author: olbed
License: UNKNOWN
Platform: UNKNOWN
Requires-Dist: pygame (<2,>=1.9.6)
Requires-Dist: PyYAML (<6,>=5.3.1)
